structurizr_py/__init__.py
structurizr_py-0.1.0.dist-info/LICENSE
structurizr_py-0.1.0.dist-info/METADATA
structurizr_py-0.1.0.dist-info/WHEEL
structurizr_py-0.1.0.dist-info/top_level.txt
structurizr_py-0.1.0.dist-info/RECORD
