Metadata-Version: 2.1
Name: structurizr-py
Version: 0.1.0
Summary: Python client library for Structurizr
Home-page: https://github.com/ysholomii/structurizr_py
Author: Yurii Sholomii
Author-email: yuriy.sholomiy@gmail.com
License: Apache-2.0
Platform: UNKNOWN
